tovald/__init__.py
tovald/conf.py
tovald/main.py
tovald/static/toctree.j2
tovald-0.1.6.dist-info/METADATA
tovald-0.1.6.dist-info/WHEEL
tovald-0.1.6.dist-info/entry_points.txt
tovald-0.1.6.dist-info/top_level.txt
tovald-0.1.6.dist-info/RECORD
