Metadata-Version: 2.1
Name: tovald
Version: 0.1.6
Summary: Publish rich markdown documentation to Confluence
Author-email: Charles SENGES <charles.senges.io+github@protonmail.com>
License: GNU GPLv3+
Classifier: License :: OSI Approved :: GNU General Public License v3 or later (GPLv3+)
Requires-Python: >=3.12
Requires-Dist: myst-parser==4.0
Requires-Dist: sphinx==8.1
Requires-Dist: sphinx-toolbox==3.8
Requires-Dist: sphinxcontrib-confluencebuilder==2.8
